{"name":"Búsqueda de canciones/artistas","id":"búsqueda-de-contenido-en-spotify;búsqueda-de-canciones/artistas","scenarioId":"classpath:features/search:Búsqueda de canciones/artistas","methodName":"Búsqueda de canciones/artistas","testSteps":[{"number":1,"description":"Dado que Jose está en la página principal de Spotify Web","duration":18163,"startTime":"2025-11-17T04:35:06.791458950Z[Etc/UTC]","screenshots":[{"screenshot":"b38427af6add025bc9f4ee3c623797764a0c3ca38c4fe828ebc30e501c0ce3ec.png","timeStamp":1763354124956,"screenshotName":"b38427af6add025bc9f4ee3c623797764a0c3ca38c4fe828ebc30e501c0ce3ec.png"}],"result":"SUCCESS","precondition":false,"level":0,"children":[{"number":2,"description":"Jose navigate to","duration":17893,"startTime":"2025-11-17T04:35:07.060644548Z[Etc/UTC]","screenshots":[{"screenshot":"b38427af6add025bc9f4ee3c623797764a0c3ca38c4fe828ebc30e501c0ce3ec.png","timeStamp":1763354124954,"screenshotName":"b38427af6add025bc9f4ee3c623797764a0c3ca38c4fe828ebc30e501c0ce3ec.png"}],"result":"SUCCESS","precondition":false,"level":1,"children":[{"number":3,"description":"Jose opens the browser at https://open.spotify.com/","duration":17867,"startTime":"2025-11-17T04:35:07.081517291Z[Etc/UTC]","screenshots":[{"screenshot":"b38427af6add025bc9f4ee3c623797764a0c3ca38c4fe828ebc30e501c0ce3ec.png","timeStamp":1763354124949,"screenshotName":"b38427af6add025bc9f4ee3c623797764a0c3ca38c4fe828ebc30e501c0ce3ec.png"}],"result":"SUCCESS","precondition":false,"level":2}]}]},{"number":4,"description":"Cuando busca el término \"Coldplay\"","duration":1172,"startTime":"2025-11-17T04:35:24.956788028Z[Etc/UTC]","screenshots":[{"screenshot":"c8b676c390f3ec0946b216727aafd19fea353578faced7cb987fb8b22951eb3d.png","timeStamp":1763354126131,"screenshotName":"c8b676c390f3ec0946b216727aafd19fea353578faced7cb987fb8b22951eb3d.png"}],"result":"SUCCESS","precondition":false,"level":0,"children":[{"number":5,"description":"Jose search","duration":1156,"startTime":"2025-11-17T04:35:24.971442178Z[Etc/UTC]","screenshots":[{"screenshot":"c8b676c390f3ec0946b216727aafd19fea353578faced7cb987fb8b22951eb3d.png","timeStamp":1763354126128,"screenshotName":"c8b676c390f3ec0946b216727aafd19fea353578faced7cb987fb8b22951eb3d.png"}],"result":"SUCCESS","precondition":false,"level":1,"children":[{"number":6,"description":"Jose enters \u0027Coldplay\u0027 then hits [ENTER] into Search input","duration":1059,"startTime":"2025-11-17T04:35:25.065266387Z[Etc/UTC]","screenshots":[{"screenshot":"c8b676c390f3ec0946b216727aafd19fea353578faced7cb987fb8b22951eb3d.png","timeStamp":1763354126124,"screenshotName":"c8b676c390f3ec0946b216727aafd19fea353578faced7cb987fb8b22951eb3d.png"}],"result":"SUCCESS","precondition":false,"level":2}]}]},{"number":7,"description":"Entonces debería visualizar resultados relacionados con \"Coldplay\"","duration":2510,"startTime":"2025-11-17T04:35:26.131690808Z[Etc/UTC]","screenshots":[{"screenshot":"37f14308cbe347dd94feddc706524d1388fc1be9ad5d7cd5f13eae3fd5448ef5.png","timeStamp":1763354128643,"screenshotName":"37f14308cbe347dd94feddc706524d1388fc1be9ad5d7cd5f13eae3fd5448ef5.png"}],"result":"SUCCESS","precondition":false,"level":0,"children":[{"number":8,"description":"Jose should see  that is true","duration":1980,"startTime":"2025-11-17T04:35:26.160272322Z[Etc/UTC]","screenshots":[{"screenshot":"7de1641095bc341262ec80459d809f4f7acab512c9859001b4738bef4e6ee85f.png","timeStamp":1763354128140,"screenshotName":"7de1641095bc341262ec80459d809f4f7acab512c9859001b4738bef4e6ee85f.png"}],"result":"SUCCESS","precondition":false,"level":1},{"number":9,"description":"Jose should see  that is true","duration":493,"startTime":"2025-11-17T04:35:28.147779070Z[Etc/UTC]","screenshots":[{"screenshot":"37f14308cbe347dd94feddc706524d1388fc1be9ad5d7cd5f13eae3fd5448ef5.png","timeStamp":1763354128641,"screenshotName":"37f14308cbe347dd94feddc706524d1388fc1be9ad5d7cd5f13eae3fd5448ef5.png"}],"result":"SUCCESS","precondition":false,"level":1}]}],"userStory":{"id":"classpath:features/search","storyName":"Búsqueda de contenido en Spotify","displayName":"Búsqueda de contenido en Spotify","path":"search","pathElements":[{"name":"search","description":""}],"type":"feature"},"title":"Búsqueda de canciones/artistas","description":"","tags":[{"name":"Linux","type":"context","displayName":"Linux"},{"name":"search","type":"tag","displayName":"search"},{"name":"Chrome","type":"context","displayName":"Chrome"},{"name":"Chrome, Linux","type":"context","displayName":"Chrome, Linux"}],"startTime":"2025-11-17T04:35:06.680017221Z[Etc/UTC]","endTime":"2025-11-17T04:35:28.643735134Z[Etc/UTC]","duration":21963,"projectKey":"","driver":"chrome:jose","isManualTestingUpToDate":false,"context":"chrome,linux","manual":false,"testSource":"Cucumber","actors":[{"name":"Jose"}],"result":"SUCCESS"}